<?xml version="1.0" encoding="utf-8"?>
<!DOCTYPE hibernate-mapping PUBLIC "-//Hibernate/Hibernate Mapping DTD 3.0//EN"
"http://www.hibernate.org/dtd/hibernate-mapping-3.0.dtd">
<!-- 
    Mapping file autogenerated by MyEclipse Persistence Tools
-->
<hibernate-mapping>
    <class name="com.whnr.cac.database.BtbMonitordevicediagdetail" table="btb_monitordevicediagdetail" catalog="intecomp_display">
        <id name="monitorDeviceDiagDetailId" type="java.lang.String">
            <column name="MonitorDeviceDiagDetailID" />
            <generator class="assigned" />
        </id>
        <many-to-one name="btbMonitordevicediagnose" class="com.whnr.cac.database.BtbMonitordevicediagnose" fetch="select">
            <column name="MonitorDeviceDiagnoseID" not-null="true" />
        </many-to-one>
        <many-to-one name="btbMonitordevicediagmode" class="com.whnr.cac.database.BtbMonitordevicediagmode" fetch="select">
            <column name="MonitorDeviceDiagModeID" not-null="true" />
        </many-to-one>
        <property name="monitorDeviceDiagResult" type="java.lang.String">
            <column name="MonitorDeviceDiagResult" length="50" />
        </property>
    </class>
</hibernate-mapping>
